{
  "version": "7",
  "dialect": "sqlite",
  "entries": [
    {
      "idx": 0,
      "version": "6",
      "when": 1728133964232,
      "tag": "0000_same_squadron_sinister",
      "breakpoints": true
    },
    {
      "idx": 1,
      "version": "6",
      "when": 1729701360206,
      "tag": "0001_strange_phantom_reporter",
      "breakpoints": true
    },
    {
      "idx": 2,
      "version": "6",
      "when": 1729778725632,
      "tag": "0002_shiny_may_parker",
      "breakpoints": true
    },
    {
      "idx": 3,
      "version": "6",
      "when": 1729852423708,
      "tag": "0003_mushy_smasher",
      "breakpoints": true
    },
    {
      "idx": 4,
      "version": "6",
      "when": 1730507982541,
      "tag": "0004_special_doctor_octopus",
      "breakpoints": true
    },
    {
      "idx": 5,
      "version": "6",
      "when": 1730668759272,
      "tag": "0005_bizarre_penance",
      "breakpoints": true
    },
    {
      "idx": 6,
      "version": "6",
      "when": 1730669169994,
      "tag": "0006_gigantic_brother_voodoo",
      "breakpoints": true
    },
    {
      "idx": 7,
      "version": "6",
      "when": 1730669332681,
      "tag": "0007_salty_squadron_supreme",
      "breakpoints": true
    },
    {
      "idx": 8,
      "version": "6",
      "when": 1730669535964,
      "tag": "0008_shiny_bug",
      "breakpoints": true
    },
    {
      "idx": 9,
      "version": "6",
      "when": 1730669651676,
      "tag": "0009_cuddly_stardust",
      "breakpoints": true
    },
    {
      "idx": 10,
      "version": "6",
      "when": 1730733083097,
      "tag": "0010_sharp_boomerang",
      "breakpoints": true
    },
    {
      "idx": 11,
      "version": "6",
      "when": 1731084520715,
      "tag": "0011_nostalgic_devos",
      "breakpoints": true
    },
    {
      "idx": 12,
      "version": "6",
      "when": 1731513438599,
      "tag": "0012_workable_vertigo",
      "breakpoints": true
    },
    {
      "idx": 13,
      "version": "6",
      "when": 1731958080746,
      "tag": "0013_nifty_doctor_octopus",
      "breakpoints": true
    },
    {
      "idx": 14,
      "version": "6",
      "when": 1731958306202,
      "tag": "0014_large_puff_adder",
      "breakpoints": true
    },
    {
      "idx": 15,
      "version": "6",
      "when": 1731958420709,
      "tag": "0015_minor_fat_cobra",
      "breakpoints": true
    },
    {
      "idx": 16,
      "version": "6",
      "when": 1731958639314,
      "tag": "0016_good_enchantress",
      "breakpoints": true
    },
    {
      "idx": 17,
      "version": "6",
      "when": 1732101222344,
      "tag": "0017_moaning_mystique",
      "breakpoints": true
    },
    {
      "idx": 18,
      "version": "6",
      "when": 1733229795199,
      "tag": "0018_steep_chimera",
      "breakpoints": true
    },
    {
      "idx": 19,
      "version": "6",
      "when": 1738180132823,
      "tag": "0019_productive_leopardon",
      "breakpoints": true
    }
  ]
}